damv1dotenvsecretdec/__init__.py
damv1dotenvsecretdec/openssl.py
damv1dotenvsecretdec-0.1.0.dist-info/LICENSE
damv1dotenvsecretdec-0.1.0.dist-info/METADATA
damv1dotenvsecretdec-0.1.0.dist-info/WHEEL
damv1dotenvsecretdec-0.1.0.dist-info/top_level.txt
damv1dotenvsecretdec-0.1.0.dist-info/RECORD
